Metadata-Version: 2.1
Name: djangorestframework-camel-case
Version: 1.1.1
Summary: Camel case JSON support for Django REST framework.
Home-page: https://github.com/vbabiy/djangorestframework-camel-case
Author: Vitaly Babiy
Author-email: vbabiy86@gmail.com
License: BSD
Keywords: djangorestframework_camel_case
Platform: UNKNOWN
Classifier: Development Status :: 2 - Pre-Alpha
Classifier: Intended Audience :: Developers
Classifier: License :: OSI Approved :: BSD License
Classifier: Natural Language :: English
Classifier: Programming Language :: Python :: 3
Classifier: Programming Language :: Python :: 3.6
Classifier: Programming Language :: Python :: 3.7
